tagflow/__init__.py
tagflow/py.typed
tagflow/tagflow.py
tagflow/static/tagflow.js
tagflow-0.12.0.dist-info/METADATA
tagflow-0.12.0.dist-info/WHEEL
tagflow-0.12.0.dist-info/licenses/LICENSE
tagflow-0.12.0.dist-info/RECORD
