Metadata-Version: 2.4
Name: tagflow
Version: 0.12.0
Summary: Block-oriented HTML generation that works with ordinary control flow
Project-URL: Homepage, https://github.com/lessrest/tagflow
Project-URL: Bug Tracker, https://github.com/lessrest/tagflow/issues
Project-URL: Repository, https://github.com/lessrest/tagflow
Author-email: Mikael Brockman <mikael@brockman.se>
License-Expression: MIT
License-File: LICENSE
Classifier: License :: OSI Approved :: MIT License
Classifier: Programming Language :: Python :: 3.12
Classifier: Topic :: Internet :: WWW/HTTP :: Dynamic Content
Classifier: Topic :: Text Processing :: Markup :: HTML
Classifier: Topic :: Text Processing :: Markup :: XML
Requires-Python: >=3.12
Requires-Dist: anyio>=4.8.0
Requires-Dist: beautifulsoup4>=4.12.3
Requires-Dist: fastapi>=0.115.6
Requires-Dist: hypercorn>=0.17.3
Requires-Dist: rich>=13.9.4
Requires-Dist: trio>=0.28.0
